{
  "active": true,
  "application": "7fabc188db030010ab0a4870399619f3",
  "assessment": null,
  "content_page": null,
  "device_type": null,
  "filter": null,
  "hint": null,
  "homepage": null,
  "image": null,
  "link_type": "LIST",
  "map_page": null,
  "mobile_title": "snow cicd Table",
  "mobile_view_name": "Mobile",
  "name": "x_339650_snow_cicd_table",
  "order": null,
  "override_menu_roles": false,
  "query": null,
  "report": null,
  "roles": "x_339650_snow_cicd.user",
  "sys_class_name": "sys_app_module",
  "sys_created_by": "admin",
  "sys_created_on": "2020-02-13 19:37:31",
  "sys_id": "18bbc588db030010ab0a48703996199a",
  "sys_mod_count": 0,
  "sys_name": "snow cicd Table",
  "sys_package": "2fab0588db030010ab0a487039961921",
  "sys_policy": null,
  "sys_scope": "2fab0588db030010ab0a487039961921",
  "sys_update_name": "sys_app_module_18bbc588db030010ab0a48703996199a",
  "sys_updated_by": "admin",
  "sys_updated_on": "2020-02-13 19:37:31",
  "timeline_page": null,
  "title": "snow cicd Table",
  "uncancelable": false,
  "view_name": null,
  "window_name": null
}
